tlcc_auth/README.md
tlcc_auth/__init__.py
tlcc_auth/admin.py
tlcc_auth/apps.py
tlcc_auth/conf.py
tlcc_auth/forms.py
tlcc_auth/jwt_views.py
tlcc_auth/models.py
tlcc_auth/session_utils.py
tlcc_auth/signals.py
tlcc_auth/urls.py
tlcc_auth/views.py
tlcc_auth/__pycache__/__init__.cpython-313.pyc
tlcc_auth/__pycache__/admin.cpython-313.pyc
tlcc_auth/__pycache__/apps.cpython-313.pyc
tlcc_auth/__pycache__/conf.cpython-313.pyc
tlcc_auth/__pycache__/forms.cpython-313.pyc
tlcc_auth/__pycache__/jwt_views.cpython-313.pyc
tlcc_auth/__pycache__/models.cpython-313.pyc
tlcc_auth/__pycache__/session_utils.cpython-313.pyc
tlcc_auth/__pycache__/signals.cpython-313.pyc
tlcc_auth/__pycache__/urls.cpython-313.pyc
tlcc_auth/__pycache__/views.cpython-313.pyc
tlcc_auth/migrations/0001_initial.py
tlcc_auth/migrations/__init__.py
tlcc_auth/migrations/__pycache__/0001_initial.cpython-313.pyc
tlcc_auth/migrations/__pycache__/__init__.cpython-313.pyc
tlcc_auth/rest/__init__.py
tlcc_auth/rest/serializers.py
tlcc_auth/rest/urls.py
tlcc_auth/rest/views.py
tlcc_auth/rest/__pycache__/__init__.cpython-313.pyc
tlcc_auth/rest/__pycache__/serializers.cpython-313.pyc
tlcc_auth/rest/__pycache__/urls.cpython-313.pyc
tlcc_auth/rest/__pycache__/views.cpython-313.pyc
tlcc_auth/templates/tlcc_auth/base_auth.html
tlcc_auth/templates/tlcc_auth/login.html
tlcc_auth/templates/tlcc_auth/password_change_done.html
tlcc_auth/templates/tlcc_auth/password_change_form.html
tlcc_auth/templates/tlcc_auth/password_reset_complete.html
tlcc_auth/templates/tlcc_auth/password_reset_confirm.html
tlcc_auth/templates/tlcc_auth/password_reset_done.html
tlcc_auth/templates/tlcc_auth/password_reset_form.html
tlcc_auth/templates/tlcc_auth/profile.html
tlcc_auth/templates/tlcc_auth/register.html
tlcc_auth/templates/tlcc_auth/sessions.html
tlcc_auth/templates/tlcc_auth/sessions_admin.html
tlcc_auth/templates/tlcc_auth/tokens.html
tlcc_auth/templates/tlcc_auth/email/password_reset_email.html
django_tlcc_auth-0.1.5.dist-info/METADATA
django_tlcc_auth-0.1.5.dist-info/WHEEL
django_tlcc_auth-0.1.5.dist-info/top_level.txt
django_tlcc_auth-0.1.5.dist-info/RECORD
