Metadata-Version: 2.4
Name: django-tlcc-auth
Version: 0.1.5
Summary: TLCC reusable Django authentication app
Author-email: Lowie <Vanhaesbroucklowie@gmail.com>
License: MIT
Requires-Python: >=3.10
Requires-Dist: Django>=4.2
Requires-Dist: djangorestframework>=3.13
Provides-Extra: jwt
Requires-Dist: djangorestframework-simplejwt>=5.0; extra == "jwt"
Requires-Dist: PyJWT>=2.6; extra == "jwt"
